corrscope/__init__.py
corrscope/__main__.py
corrscope/channel.py
corrscope/cli.py
corrscope/config.py
corrscope/corrscope.py
corrscope/designNotes.md
corrscope/layout.py
corrscope/outputs.py
corrscope/renderer.py
corrscope/spectrum.py
corrscope/triggers.py
corrscope/util.py
corrscope/version.py
corrscope/wave.py
corrscope/wave_common.py
corrscope/generate/__init__.py
corrscope/gui/.gitignore
corrscope/gui/__init__.py
corrscope/gui/history_file_dlg.py
corrscope/gui/model_bind.py
corrscope/gui/translate.pro
corrscope/gui/util.py
corrscope/gui/version_common.py
corrscope/gui/view_mainwindow.py
corrscope/gui/view_stack.py
corrscope/gui/widgets.py
corrscope/settings/__init__.py
corrscope/settings/global_prefs.py
corrscope/settings/paths.py
corrscope/utils/__init__.py
corrscope/utils/profile_wrapper.py
corrscope/utils/trigger_util.py
corrscope/utils/wavprobe.py
corrscope/utils/windows.py
corrscope/utils/scipy/__init__.py
corrscope/utils/scipy/signal.py
corrscope/utils/scipy/wavfile.py
corrscope/utils/scipy/windows.py
corrscope-0.11.0.dist-info/METADATA
corrscope-0.11.0.dist-info/WHEEL
corrscope-0.11.0.dist-info/entry_points.txt
corrscope-0.11.0.dist-info/licenses/LICENSE
corrscope-0.11.0.dist-info/RECORD
