Metadata-Version: 2.4
Name: corrscope
Version: 0.11.0
Summary: Python program to render wave files into oscilloscope views, featuring advanced correlation-based triggering algorithm
Project-URL: Repository, https://github.com/corrscope/corrscope/
Project-URL: Documentation, https://corrscope.github.io/corrscope/
Author-email: nyanpasu64 <nyanpasu64@tuta.io>
License-Expression: BSD-2-Clause
License-File: LICENSE
Requires-Python: ~=3.10
Requires-Dist: appdirs<2,>=1.4.4
Requires-Dist: appnope<0.2,>=0.1.3; sys_platform == 'darwin'
Requires-Dist: atomicwrites<2,>=1.4.0
Requires-Dist: attrs>=21.2.0
Requires-Dist: click<9,>=8.0.1
Requires-Dist: colorspacious<2,>=1.1.2
Requires-Dist: matplotlib~=3.5
Requires-Dist: numpy<3.0,>=1.21
Requires-Dist: qtpy<3,>=2.0.1
Requires-Dist: ruamel-yaml<0.19,>=0.17
Provides-Extra: qt5
Requires-Dist: pyqt5-qt5<5.15.11,~=5.15; extra == 'qt5'
Requires-Dist: pyqt5~=5.15; extra == 'qt5'
Provides-Extra: qt6
Requires-Dist: pyqt6~=6.2; extra == 'qt6'
